drongo/__init__.py
drongo/app.py
drongo/exceptions.py
drongo/request.py
drongo/response.py
drongo/response_headers.py
drongo/status_codes.py
drongo/managers/__init__.py
drongo/managers/middleware.py
drongo/managers/url.py
drongo/tests/__init__.py
drongo/tests/test_dict2.py
drongo/tests/test_drongo.py
drongo/tests/test_request.py
drongo/tests/test_response.py
drongo/utils/__init__.py
drongo/utils/dict2.py
drongo_core-1.0.2.dist-info/METADATA
drongo_core-1.0.2.dist-info/RECORD
drongo_core-1.0.2.dist-info/WHEEL
drongo_core-1.0.2.dist-info/entry_points.txt
drongo_core-1.0.2.dist-info/top_level.txt
drongo_core-1.0.2.dist-info/zip-safe
drongo_utils/__init__.py
drongo_utils/endpoint.py
drongo_utils/helpers.py
nest/__init__.py
nest/cmd.py
nest/nest.py
nest/reloader.py
nest/handlers/__init__.py
nest/handlers/asynch.py
nest/handlers/sync.py
nest/parsers/__init__.py
nest/parsers/header.py
nest/parsers/http.py
nest/parsers/request.py
nest/parsers/body/__init__.py
nest/parsers/body/body.py
nest/parsers/body/multipart.py
nest/parsers/body/raw.py
nest/parsers/body/urlencoded.py
nest/parsers/body/utils.py
nest/tests/__init__.py
nest/tests/parsers/__init__.py
nest/tests/parsers/test_header.py
nest/tests/parsers/test_http.py
nest/tests/parsers/test_request.py
nest/tests/parsers/body/__init__.py
nest/tests/parsers/body/test_body.py
nest/tests/parsers/body/test_multipart.py
nest/tests/parsers/body/test_raw.py
nest/tests/parsers/body/test_urlencoded.py
